<?xml version="1.0" encoding="UTF-8"?>

<!--

 This file is part of the Sylius package.

 (c) Paweł Jędrzejewski

 For the full copyright and license information, please view the LICENSE
 file that was distributed with this source code.

-->

<container xmlns="http://symfony.com/schema/dic/services"
           xmlns:xsi="http://www.w3.org/2001/XMLSchema-instance"
           xsi:schemaLocation="http://symfony.com/schema/dic/services
                               http://symfony.com/schema/dic/services/services-1.0.xsd">

    <parameters>
        <parameter key="sylius.form.type.gender.class">Sylius\Bundle\UserBundle\Form\Type\GenderType</parameter>
        <parameter key="sylius.listener.customer_aware.class">Sylius\Bundle\UserBundle\EventListener\CustomerAwareListener</parameter>
        <parameter key="sylius.form.event_subscriber.set_customer_type.class">Sylius\Bundle\UserBundle\Form\EventSubscriber\SetCustomerFormSubscriber</parameter>
        <parameter key="sylius.user.validator.customer_initializer.class">Sylius\Bundle\UserBundle\Validator\Initializer\CustomerInitializer</parameter>
    </parameters>

    <services>
        <service id="sylius.form.type.gender" class="%sylius.form.type.gender.class%">
            <tag name="form.type" alias="sylius_gender" />
        </service>

        <!-- Validators -->
        <service id="sylius.user.validator.customer_initializer" class="%sylius.user.validator.customer_initializer.class%">
            <argument type="service" id="sylius.user.canonicalizer" />
            <tag name="validator.initializer" />
        </service>
    </services>

</container>
