<?xml version="1.0" ?>

<!--

 This file is part of the Sylius package.

 (c) Paweł Jędrzejewski

 For the full copyright and license information, please view the LICENSE
 file that was distributed with this source code.

-->

<resources xmlns="https://api-platform.com/schema/metadata"
           xmlns:xsi="http://www.w3.org/2001/XMLSchema-instance"
           xsi:schemaLocation="https://api-platform.com/schema/metadata https://api-platform.com/schema/metadata/metadata-2.0.xsd"
>
    <resource class="%sylius.model.shop_user.class%" shortName="User">
        <graphql>
            <operation name="shop_login">
                <attribute name="mutation">api_platform.login_mutation_resolver</attribute>
                <attribute name="write">false</attribute>
                <attribute name="args">
                    <attribute name="username">
                        <attribute name="type">String</attribute>
                    </attribute>
                    <attribute name="password">
                        <attribute name="type">String</attribute>
                    </attribute>
                </attribute>
            </operation>
        </graphql>

        <property name="id" identifier="true" writable="false"/>
    </resource>
</resources>
